[
  {
    "No.": 1,
    "Shop Name": "The Baby Shop:",
    "Location1_KH": "ភ្នំពេញ",
    "Location1_EN": "Phnom Penh",
    "Location2_KH": "ទួលគោក",
    "Location2_EN": "Tuol Kork",
    "Google map": "https://maps.app.goo.gl/B6e768mkm9hhLhaN7",
    "Contact": "https://www.facebook.com/thebabyshoptk",
    "Lat": 11.585148402651454,
    "Lng": 104.89715550674018
  },
  {
    "No.": 2,
    "Shop Name": "Kon Store Cambodia:",
    "Location1_KH": "ភ្នំពេញ",
    "Location1_EN": "Phnom Penh",
    "Location2_KH": "ទួលគោក",
    "Location2_EN": "Tuol Kork",
    "Google map": "https://maps.app.goo.gl/UG9kJMQXG9p9Gvja8",
    "Contact": "https://www.facebook.com/konstorecambodia",
    "Lat": 11.573925071022032,
    "Lng": 104.8990783067285
  },
  {
    "No.": 3,
    "Shop Name": "Dream Baby Shop",
    "Location1_KH": "ភ្នំពេញ",
    "Location1_EN": "Phnom Penh",
    "Location2_KH": "ទួលគោក",
    "Location2_EN": "Tuol Kork",
    "Google map": "https://maps.app.goo.gl/hJgykZdJL36cGXgi7",
    "Contact": "https://www.facebook.com/profile.php?id=100070279333829",
    "Lat": 11.574937679192901,
    "Lng": 104.88759920782188
  },
  {
    "No.": 4,
    "Shop Name": "Kon Ngaet Kon Nga",
    "Location1_KH": "ភ្នំពេញ",
    "Location1_EN": "Phnom Penh",
    "Location2_KH": "សែនសុខ",
    "Location2_EN": "SenSok",
    "Google map": "https://maps.app.goo.gl/nhHUdogt1Ra3RU6E7",
    "Contact": "https://www.facebook.com/media/set/?set=a.457895173017096&type=3",
    "Lat": 11.592566659808025,
    "Lng": 104.88217054904499
  },
  {
    "No.": 5,
    "Shop Name": "Ellie Baby Shop",
    "Location1_KH": "ភ្នំពេញ",
    "Location1_EN": "Phnom Penh",
    "Location2_KH": "ឬស្សីកែវ",
    "Location2_EN": "Russey Keo",
    "Google map": "https://maps.app.goo.gl/BPBV5xF26Ch2Toqj7",
    "Contact": "https://www.facebook.com/hqkhstore",
    "Lat": 11.648129919496892,
    "Lng": 104.86943586307373
  },
  {
    "No.": 6,
    "Shop Name": "Darling Baby Shop",
    "Location1_KH": "ភ្នំពេញ",
    "Location1_EN": "Phnom Penh",
    "Location2_KH": "ឬស្សីកែវ",
    "Location2_EN": "Russey Keo",
    "Google map": "https://maps.app.goo.gl/JHK6g4uMACT1R6CP8",
    "Contact": "https://www.facebook.com/profile.php?id=100068839017234",
    "Lat": 11.587469046934956,
    "Lng": 104.9057990533971
  },
  {
    "No.": 7,
    "Shop Name": "Baby’s Prestige.Kh",
    "Location1_KH": "ភ្នំពេញ",
    "Location1_EN": "Phnom Penh",
    "Location2_KH": "ពោធិ៍ចិនតុង",
    "Location2_EN": "Pochentong",
    "Google map": "https://maps.app.goo.gl/fsjT7jZdRgtXatmr7",
    "Contact": "https://www.facebook.com/Babysprestige",
    "Lat": 11.56298853317925,
    "Lng": 104.85570030673969
  },
  {
    "No.": 8,
    "Shop Name": "Kids Station",
    "Location1_KH": "ភ្នំពេញ",
    "Location1_EN": "Phnom Penh",
    "Location2_KH": "ផ្សារដើមថ្កូវ",
    "Location2_EN": "Phsar Daem Thkov",
    "Google map": "https://maps.app.goo.gl/TgHVctWvZ6KSBegb7",
    "Contact": "https://www.facebook.com/kidsstationcambodia",
    "Lat": 11.53497912349685,
    "Lng": 104.91530556296941
  },
  {
    "No.": 9,
    "Shop Name": "Baby King",
    "Location1_KH": "ភ្នំពេញ",
    "Location1_EN": "Phnom Penh",
    "Location2_KH": "ផ្សារដើមថ្កូវ",
    "Location2_EN": "Phsar Daem Thkov",
    "Google map": "https://maps.app.goo.gl/3fFxrzvwWzBKtN97A",
    "Contact": "https://www.facebook.com/profile.php?id=100087844024173",
    "Lat": 11.5311825640278,
    "Lng": 104.91513676823726
  },
  {
    "No.": 10,
    "Shop Name": "Baby land shop",
    "Location1_KH": "ភ្នំពេញ",
    "Location1_EN": "Phnom Penh",
    "Location2_KH": "ខណ្ឌដង្កោ",
    "Location2_EN": "Khan Dangkor",
    "Google map": "https://maps.app.goo.gl/NEomXt1EJbYoQ6Sn9",
    "Contact": "Telegram: 095 551 998",
    "Lat": 11.517404633565105,
    "Lng": 104.87982705955655
  },
  {
    "No.": 11,
    "Shop Name": "Mak and Oun Baby",
    "Location1_KH": "ភ្នំពេញ",
    "Location1_EN": "Phnom Penh",
    "Location2_KH": "ផ្សារដើមគរ",
    "Location2_EN": "Phsar Daem Kor",
    "Google map": "https://maps.app.goo.gl/X21XC9y4EgCDhoxz6",
    "Contact": "https://www.facebook.com/makandoun",
    "Lat": 11.558671980400174,
    "Lng": 104.9212850615421
  },
  {
    "No.": 12,
    "Shop Name": "E&M Baby Shop TTP",
    "Location1_KH": "ភ្នំពេញ",
    "Location1_EN": "Phnom Penh",
    "Location2_KH": "ទួលទំពួង",
    "Location2_EN": "Tuol Tompoung",
    "Google map": "https://maps.app.goo.gl/2FXucSPEXcXt5Zy97",
    "Contact": "https://www.facebook.com/embabyshop",
    "Lat": 11.54356705458616,
    "Lng": 104.91387418794702
  },
  {
    "No.": 13,
    "Shop Name": "Baby Collection",
    "Location1_KH": "ភ្នំពេញ",
    "Location1_EN": "Phnom Penh",
    "Location2_KH": "សន្ធរម៉ុក",
    "Location2_EN": "Santhormok",
    "Google map": "https://maps.app.goo.gl/jauTiV2WzVZ4fGEn6",
    "Contact": "https://www.facebook.com/babycollectioncambodia",
    "Lat": 11.564898691449132,
    "Lng": 104.89928073132855
  },
  {
    "No.": 14,
    "Shop Name": "Dream Baby Shop",
    "Location1_KH": "ភ្នំពេញ",
    "Location1_EN": "Phnom Penh",
    "Location2_KH": "ផ្សារកណ្តាល",
    "Location2_EN": "Psa Kandal",
    "Google map": "https://maps.app.goo.gl/6bwYiLUHBBkBuBDeA",
    "Contact": "https://www.facebook.com/profile.php?id=100070279333829",
    "Lat": 11.570712983416344,
    "Lng": 104.92664472835432
  },
  {
    "No.": 15,
    "Shop Name": "Baby cutie shop",
    "Location1_KH": "ភ្នំពេញ",
    "Location1_EN": "Phnom Penh",
    "Location2_KH": "បឹងកេងកង២",
    "Location2_EN": "Boeng Keng Kang II",
    "Google map": "https://maps.app.goo.gl/QtPTusoirgJr1dkg8",
    "Contact": "https://www.facebook.com/babycutieshopkh",
    "Lat": 11.552096956729677,
    "Lng": 104.9206892355192
  },
  {
    "No.": 16,
    "Shop Name": "Baby Love Cambodia",
    "Location1_KH": "ភ្នំពេញ",
    "Location1_EN": "Phnom Penh",
    "Location2_KH": "ចោមចៅ",
    "Location2_EN": "Chaom Chao",
    "Google map": "https://maps.app.goo.gl/ptVYnexiemtJyoJq8",
    "Contact": "https://www.facebook.com/babylovecambodia168",
    "Lat": 11.548296631087315,
    "Lng": 104.89364660917381
  },
  {
    "No.": 17,
    "Shop Name": "Niroth Baby Shop (Jing jiao)",
    "Location1_KH": "ភ្នំពេញ",
    "Location1_EN": "Phnom Penh",
    "Location2_KH": "ច្បារអំពៅ",
    "Location2_EN": "Chbar ampov",
    "Google map": "https://maps.app.goo.gl/UHsTgXaskU2Uigof8",
    "Contact": "https://www.facebook.com/profile.php?id=100068995418791",
    "Lat": 11.535139559194425,
    "Lng": 104.94651631778272
  },
  {
    "No.": 18,
    "Shop Name": "Little Newbie",
    "Location1_KH": "ភ្នំពេញ",
    "Location1_EN": "Phnom Penh",
    "Location2_KH": "ស្ទឹងមានជ័យ",
    "Location2_EN": "Stueng Mean Chey",
    "Google map": "https://www.facebook.com/profile.php?id=61572444173402",
    "Contact": "https://www.facebook.com/profile.php?id=61572444173402",
    "Lat": 11.536300295329024,
    "Lng": 104.87916670157591
  },
  {
    "No.": 19,
    "Shop Name": "Little Me",
    "Location1_KH": "ភ្នំពេញ",
    "Location1_EN": "Phnom Penh",
    "Location2_KH": "ខណ្ឌដូនពេញ",
    "Location2_EN": "Khan Doun Penh",
    "Google map": "https://maps.app.goo.gl/y6HFCmah51Gd6Deu9",
    "Contact": "https://www.facebook.com/Littlemekh",
    "Lat": 11.56399912065209,
    "Lng": 104.92180048865295
  },
  {
    "No.": 1,
    "Shop Name": "Jolie Mart",
    "Location1_KH": "ខេត្ត",
    "Location1_EN": "Provinces",
    "Location2_KH": "តាខ្មៅ",
    "Location2_EN": "Takhmau",
    "Google map": "https://maps.app.goo.gl/xNmp19uibB6F5gHG6",
    "Contact": "https://www.facebook.com/joliemart.takhmau",
    "Lat": 11.463143171655108,
    "Lng": 104.94962007612271
  },
  {
    "No.": 2,
    "Shop Name": "Leang Sry Shop",
    "Location1_KH": "ខេត្ត",
    "Location1_EN": "Provinces",
    "Location2_KH": "កំពង់ចាម",
    "Location2_EN": "Kompong Cham",
    "Google map": "https://maps.app.goo.gl/WdBfA9QSBp8rosqU8",
    "Contact": "https://www.facebook.com/leangsryshop ​",
    "Lat": 11.990065192088217,
    "Lng": 105.4655558033859
  },
  {
    "No.": 3,
    "Shop Name": "Fu Er Baby",
    "Location1_KH": "ខេត្ត",
    "Location1_EN": "Provinces",
    "Location2_KH": "កំពង់សោម",
    "Location2_EN": "Sihanuok Ville",
    "Google map": "https://maps.app.goo.gl/wE3ysJp2wJ8gce1o7",
    "Contact": "https://www.facebook.com/profile.php?id=100069955719346",
    "Lat": 10.617638881774614,
    "Lng": 103.52837497496277
  },
  {
    "No.": 4,
    "Shop Name": "The Best Baby Shop",
    "Location1_KH": "ខេត្ត",
    "Location1_EN": "Provinces",
    "Location2_KH": "កំពង់សោម",
    "Location2_EN": "Sihanuok Ville",
    "Google map": "https://maps.app.goo.gl/jnTaHKFvPFSkhPcW9",
    "Contact": "https://www.facebook.com/momphana",
    "Lat": 10.617722180517346,
    "Lng": 103.5368403419522
  },
  {
    "No.": 5,
    "Shop Name": "JK Baby House",
    "Location1_KH": "ខេត្ត",
    "Location1_EN": "Provinces",
    "Location2_KH": "បន្ទាយមានជ័យ",
    "Location2_EN": "Banteay Meanchey",
    "Google map": "https://maps.app.goo.gl/wpPvE2AEFapR749e7",
    "Contact": "https://www.facebook.com/@JkBabyHouse",
    "Lat": 13.589813214719193,
    "Lng": 102.97054542945585
  },
  {
    "No.": 6,
    "Shop Name": "My Baby Mart",
    "Location1_KH": "ខេត្ត",
    "Location1_EN": "Provinces",
    "Location2_KH": "បន្ទាយមានជ័យ",
    "Location2_EN": "Banteay Meanchey",
    "Google map": "https://maps.app.goo.gl/EtoBH4EVDX428qqH8",
    "Contact": "https://www.facebook.com/@mybabymarts",
    "Lat": 13.591564716851707,
    "Lng": 102.97276498775533
  },
  {
    "No.": 7,
    "Shop Name": "Bear Bear",
    "Location1_KH": "ខេត្ត",
    "Location1_EN": "Provinces",
    "Location2_KH": "បន្ទាយមានជ័យ",
    "Location2_EN": "Banteay Meanchey",
    "Google map": "https://maps.app.goo.gl/5nAB5wpuqRoXh9Jb9",
    "Contact": "https://www.facebook.com/profile.php?id=100089607615621",
    "Lat": 13.585978949516443,
    "Lng": 102.97263927695614
  },
  {
    "No.": 8,
    "Shop Name": "Prinna Town",
    "Location1_KH": "ខេត្ត",
    "Location1_EN": "Provinces",
    "Location2_KH": "ប៉ោយប៉ែត",
    "Location2_EN": "Poi Pet",
    "Google map": "https://maps.app.goo.gl/6zLyhyem4KyCsDyj6",
    "Contact": "https://www.facebook.com/PrinnaTown168",
    "Lat": 13.654909760011233,
    "Lng": 102.56054489126664
  },
  {
    "No.": 9,
    "Shop Name": "Phanna Baby Mart",
    "Location1_KH": "ខេត្ត",
    "Location1_EN": "Provinces",
    "Location2_KH": "កៀនស្វាយ",
    "Location2_EN": "Kien Svay",
    "Google map": "https://maps.app.goo.gl/BRNGCvKMqFsBBCAa9",
    "Contact": "https://www.facebook.com/profile.php?id=100011566964819",
    "Lat": 11.514202132373201,
    "Lng": 105.0338704587596
  }
]
